mediatpy/__init__.py
mediatpy/py.typed
mediatpy-0.2.1.dist-info/METADATA
mediatpy-0.2.1.dist-info/WHEEL
mediatpy-0.2.1.dist-info/RECORD
