Metadata-Version: 2.1
Name: mediatpy
Version: 0.2.1
Summary: Mediator implementation in Python
Home-page: https://github.com/panicoenlaxbox/mediatpy
Keywords: mediator
Author: Sergio León
Author-email: panicoenlaxbox@gmail.com
Requires-Python: >=3.10,<4.0
Classifier: Operating System :: OS Independent
Classifier: Programming Language :: Python :: 3
Classifier: Programming Language :: Python :: 3.10
Classifier: Programming Language :: Python :: 3.11
Project-URL: Documentation, https://mediatpy.readthedocs.io/en/latest/
Project-URL: Repository, https://github.com/panicoenlaxbox/mediatpy
